Fcode_Calculator/Conversions.py
Fcode_Calculator/Electronics.py
Fcode_Calculator/Scientific.py
Fcode_Calculator/__init__.py
Fcode_Calculator-1.0.1.dist-info/LICENSE.txt
Fcode_Calculator-1.0.1.dist-info/METADATA
Fcode_Calculator-1.0.1.dist-info/WHEEL
Fcode_Calculator-1.0.1.dist-info/top_level.txt
Fcode_Calculator-1.0.1.dist-info/RECORD
