Metadata-Version: 2.2
Name: Fcode_Calculator
Version: 1.0.1
Summary: A Python package for scientific and electronic calculations
Home-page: https://github.com/fcode101/pyscience.git
Author: F-Code 101
Author-email: techwbro@example.com
Classifier: Programming Language :: Python :: 3
Classifier: License :: OSI Approved :: MIT License
Classifier: Operating System :: OS Independent
Requires-Python: >=3.6
License-File: LICENSE.txt
Dynamic: author
Dynamic: author-email
Dynamic: classifier
Dynamic: description
Dynamic: description-content-type
Dynamic: home-page
Dynamic: requires-python
Dynamic: summary
